<annotation>
	<folder></folder>
	<filename>136_jpg.rf.18c2edbf641503332701cbe315d709ee.jpg</filename>
	<path>136_jpg.rf.18c2edbf641503332701cbe315d709ee.jpg</path>
	<source>
		<database>roboflow.com</database>
	</source>
	<size>
		<width>640</width>
		<height>640</height>
		<depth>3</depth>
	</size>
	<segmented>0</segmented>
	<object>
		<name>RPMU</name>
		<pose>Unspecified</pose>
		<truncated>0</truncated>
		<difficult>0</difficult>
		<occluded>0</occluded>
		<bndbox>
			<xmin>206</xmin>
			<xmax>238</xmax>
			<ymin>162</ymin>
			<ymax>304</ymax>
		</bndbox>
		<polygon>
			<x1>205.151854</x1>
			<y1>299.511153</y1>
			<x2>228.352294</x2>
			<y2>303.258794</y2>
			<x3>237.130856</x3>
			<y3>274.526818</y3>
			<x4>235.249719</x4>
			<y4>167.094198</y4>
			<x5>215.089158</x5>
			<y5>161.375001</y5>
			<x6>205.151854</x6>
			<y6>299.511153</y6>
		</polygon>
	</object>
	<object>
		<name>RPMU</name>
		<pose>Unspecified</pose>
		<truncated>0</truncated>
		<difficult>0</difficult>
		<occluded>0</occluded>
		<bndbox>
			<xmin>233</xmin>
			<xmax>264</xmax>
			<ymin>181</ymin>
			<ymax>311</ymax>
		</bndbox>
		<polygon>
			<x1>232.114521</x1>
			<y1>298.261956</y1>
			<x2>242.774221</x2>
			<y2>309.504878</y2>
			<x3>263.466494</x3>
			<y3>283.271345</y3>
			<x4>251.552783</x4>
			<y4>179.586364</y4>
			<x5>237.823111</x5>
			<y5>183.250001</y5>
			<x6>232.114521</x6>
			<y6>298.261956</y6>
		</polygon>
	</object>
	<object>
		<name>RCU</name>
		<pose>Unspecified</pose>
		<truncated>0</truncated>
		<difficult>0</difficult>
		<occluded>0</occluded>
		<bndbox>
			<xmin>246</xmin>
			<xmax>280</xmax>
			<ymin>167</ymin>
			<ymax>297</ymax>
		</bndbox>
		<polygon>
			<x1>274.753223</x1>
			<y1>238.299514</y1>
			<x2>278.51545</x2>
			<y2>167.094198</y2>
			<x3>258.989207</x3>
			<y3>166.062501</y3>
			<x4>245.282388</x4>
			<y4>268.280734</y4>
			<x5>249.044615</x5>
			<y5>295.763512</y5>
			<x6>262.212434</x6>
			<y6>292.015872</y6>
			<x7>274.753223</x7>
			<y7>238.299514</y7>
		</polygon>
	</object>
	<object>
		<name>RIU</name>
		<pose>Unspecified</pose>
		<truncated>0</truncated>
		<difficult>0</difficult>
		<occluded>0</occluded>
		<bndbox>
			<xmin>262</xmin>
			<xmax>298</xmax>
			<ymin>177</ymin>
			<ymax>322</ymax>
		</bndbox>
		<polygon>
			<x1>260.958374</x1>
			<y1>295.763512</y1>
			<x2>278.51545</x2>
			<y2>320.747848</y2>
			<x3>290.429209</x3>
			<y3>304.508039</y3>
			<x4>294.818466</x4>
			<y4>230.804232</y4>
			<x5>296.699604</x5>
			<y5>175.838676</y5>
			<x6>277.803513</x6>
			<y6>181.687501</y6>
			<x7>269.736888</x7>
			<y7>259.536207</y7>
			<x8>260.958374</x8>
			<y8>295.763512</y8>
		</polygon>
	</object>
	<object>
		<name>RIU</name>
		<pose>Unspecified</pose>
		<truncated>0</truncated>
		<difficult>0</difficult>
		<occluded>0</occluded>
		<bndbox>
			<xmin>291</xmin>
			<xmax>318</xmax>
			<ymin>168</ymin>
			<ymax>323</ymax>
		</bndbox>
		<polygon>
			<x1>291.683269</x1>
			<y1>320.747848</y1>
			<x2>316.764847</x2>
			<y2>321.997045</y2>
			<x3>316.764847</x3>
			<y3>278.274459</y3>
			<x4>311.512479</x4>
			<y4>169.187501</y4>
			<x5>296.072574</x5>
			<y5>167.094198</y5>
			<x6>289.802179</x6>
			<y6>293.265069</y6>
			<x7>291.683269</x7>
			<y7>320.747848</y7>
		</polygon>
	</object>
	<object>
		<name>RMU</name>
		<pose>Unspecified</pose>
		<truncated>0</truncated>
		<difficult>0</difficult>
		<occluded>0</occluded>
		<bndbox>
			<xmin>164</xmin>
			<xmax>212</xmax>
			<ymin>148</ymin>
			<ymax>283</ymax>
		</bndbox>
		<polygon>
			<x1>163.140182</x1>
			<y1>265.782291</y1>
			<x2>205.778884</x2>
			<y2>282.022099</y2>
			<x3>211.422249</x3>
			<y3>245.794843</y3>
			<x4>204.524824</x4>
			<y4>188.330844</y4>
			<x5>204.524824</x5>
			<y5>155.851227</y5>
			<x6>170.405179</x6>
			<y6>147.312501</y6>
			<x7>166.902457</x7>
			<y7>232.05343</y7>
			<x8>163.140182</x8>
			<y8>265.782291</y8>
		</polygon>
	</object>
	<object>
		<name>LIU</name>
		<pose>Unspecified</pose>
		<truncated>0</truncated>
		<difficult>0</difficult>
		<occluded>0</occluded>
		<bndbox>
			<xmin>316</xmin>
			<xmax>348</xmax>
			<ymin>151</ymin>
			<ymax>328</ymax>
		</bndbox>
		<polygon>
			<x1>314.883757</x1>
			<y1>315.750961</y1>
			<x2>340.592365</x2>
			<y2>326.993931</y2>
			<x3>343.727562</x3>
			<y3>270.779178</y3>
			<x4>347.489789</x4>
			<y4>149.605144</y4>
			<x5>325.623209</x5>
			<y5>153.562501</y5>
			<x6>314.883757</x6>
			<y6>315.750961</y6>
		</polygon>
	</object>
	<object>
		<name>LIU</name>
		<pose>Unspecified</pose>
		<truncated>0</truncated>
		<difficult>0</difficult>
		<occluded>0</occluded>
		<bndbox>
			<xmin>346</xmin>
			<xmax>369</xmax>
			<ymin>168</ymin>
			<ymax>318</ymax>
		</bndbox>
		<polygon>
			<x1>347.489789</x1>
			<y1>314.501764</y1>
			<x2>361.284686</x2>
			<y2>317.000206</y2>
			<x3>368.18211</x3>
			<y3>289.517429</y3>
			<x4>363.251823</x4>
			<y4>172.312501</y4>
			<x5>348.116819</x5>
			<y5>167.094198</y5>
			<x6>344.981622</x6>
			<y6>267.031537</y6>
			<x7>347.489789</x7>
			<y7>314.501764</y7>
		</polygon>
	</object>
	<object>
		<name>LCU</name>
		<pose>Unspecified</pose>
		<truncated>0</truncated>
		<difficult>0</difficult>
		<occluded>0</occluded>
		<bndbox>
			<xmin>369</xmin>
			<xmax>397</xmax>
			<ymin>162</ymin>
			<ymax>313</ymax>
		</bndbox>
		<polygon>
			<x1>372.571367</x1>
			<y1>160.848114</y1>
			<x2>368.80914</x2>
			<y2>238.299514</y2>
			<x3>368.18211</x3>
			<y3>298.261956</y3>
			<x4>385.739186</x4>
			<y4>312.003321</y4>
			<x5>396.398885</x5>
			<y5>284.520543</y5>
			<x6>388.874431</x6>
			<y6>228.305789</y6>
			<x7>393.041142</x7>
			<y7>170.750001</y7>
			<x8>372.571367</x8>
			<y8>160.848114</y8>
		</polygon>
	</object>
	<object>
		<name>LPMU</name>
		<pose>Unspecified</pose>
		<truncated>0</truncated>
		<difficult>0</difficult>
		<occluded>0</occluded>
		<bndbox>
			<xmin>392</xmin>
			<xmax>426</xmax>
			<ymin>169</ymin>
			<ymax>298</ymax>
		</bndbox>
		<polygon>
			<x1>394.517748</x1>
			<y1>168.343395</y1>
			<x2>391.38255</x2>
			<y2>244.545597</y2>
			<x3>395.144825</x3>
			<y3>288.268183</y3>
			<x4>413.956009</x4>
			<y4>297.01271</y4>
			<x5>424.61566</x5>
			<y5>277.025261</y5>
			<x6>415.210068</x6>
			<y6>245.794843</y6>
			<x7>411.071519</x7>
			<y7>172.312501</y7>
			<x8>394.517748</x8>
			<y8>168.343395</y8>
		</polygon>
	</object>
	<object>
		<name>LPMU</name>
		<pose>Unspecified</pose>
		<truncated>0</truncated>
		<difficult>0</difficult>
		<occluded>0</occluded>
		<bndbox>
			<xmin>419</xmin>
			<xmax>446</xmax>
			<ymin>164</ymin>
			<ymax>289</ymax>
		</bndbox>
		<polygon>
			<x1>422.107541</x1>
			<y1>273.277621</y1>
			<x2>433.394174</x2>
			<y2>288.268183</y2>
			<x3>444.680903</x3>
			<y3>257.037765</y3>
			<x4>435.373332</x4>
			<y4>162.937501</y4>
			<x5>417.718188</x5>
			<y5>170.841838</y5>
			<x6>419.599325</x6>
			<y6>243.296399</y6>
			<x7>422.107541</x7>
			<y7>273.277621</y7>
		</polygon>
	</object>
	<object>
		<name>LMU</name>
		<pose>Unspecified</pose>
		<truncated>0</truncated>
		<difficult>0</difficult>
		<occluded>0</occluded>
		<bndbox>
			<xmin>442</xmin>
			<xmax>489</xmax>
			<ymin>143</ymin>
			<ymax>288</ymax>
		</bndbox>
		<polygon>
			<x1>476.921593</x1>
			<y1>158.250001</y1>
			<x2>443.426843</x2>
			<y2>142.109862</y2>
			<x3>440.918724</x3>
			<y3>255.788567</y3>
			<x4>449.07016</x4>
			<y4>287.018986</y4>
			<x5>487.946682</x5>
			<y5>247.04404</y5>
			<x6>476.921593</x6>
			<y6>158.250001</y6>
		</polygon>
	</object>
	<object>
		<name>RID</name>
		<pose>Unspecified</pose>
		<truncated>0</truncated>
		<difficult>0</difficult>
		<occluded>0</occluded>
		<bndbox>
			<xmin>290</xmin>
			<xmax>309</xmax>
			<ymin>328</ymin>
			<ymax>462</ymax>
		</bndbox>
		<polygon>
			<x1>291.000249</x1>
			<y1>457.363516</y1>
			<x2>306.765818</x2>
			<y2>460.932707</y2>
			<x3>307.986333</x3>
			<y3>411.098708</y3>
			<x4>306.808903</x4>
			<y4>327.000001</y4>
			<x5>288.850405</x5>
			<y5>339.580223</y5>
			<x6>292.075185</x6>
			<y6>393.831911</y6>
			<x7>291.000249</x7>
			<y7>457.363516</y7>
		</polygon>
	</object>
	<object>
		<name>RID</name>
		<pose>Unspecified</pose>
		<truncated>0</truncated>
		<difficult>0</difficult>
		<occluded>0</occluded>
		<bndbox>
			<xmin>266</xmin>
			<xmax>292</xmax>
			<ymin>330</ymin>
			<ymax>478</ymax>
		</bndbox>
		<polygon>
			<x1>287.77547</x1>
			<y1>401.684147</y1>
			<x2>291.000249</x2>
			<y2>338.866409</y2>
			<x3>270.344991</x3>
			<y3>329.321429</y3>
			<x4>265.202066</x4>
			<y4>361.709194</y4>
			<x5>265.202066</x5>
			<y5>471.640279</y5>
			<x6>280.251002</x6>
			<y6>476.637151</y6>
			<x7>287.77547</x7>
			<y7>401.684147</y7>
		</polygon>
	</object>
	<object>
		<name>RCD</name>
		<pose>Unspecified</pose>
		<truncated>0</truncated>
		<difficult>0</difficult>
		<occluded>0</occluded>
		<bndbox>
			<xmin>242</xmin>
			<xmax>270</xmax>
			<ymin>341</ymin>
			<ymax>475</ymax>
		</bndbox>
		<polygon>
			<x1>241.227611</x1>
			<y1>345.392858</y1>
			<x2>242.270332</x2>
			<y2>393.831911</y2>
			<x3>241.195396</x3>
			<y3>474.495642</y3>
			<x4>259.110809</x4>
			<y4>473.781788</y4>
			<x5>259.827442</x5>
			<y5>439.517562</y5>
			<x6>263.052194</x6>
			<y6>392.404256</y6>
			<x7>269.143451</x7>
			<y7>351.001636</y7>
			<x8>261.260653</x8>
			<y8>339.580223</y8>
			<x9>241.227611</x9>
			<y9>345.392858</y9>
		</polygon>
	</object>
	<object>
		<name>RPMD</name>
		<pose>Unspecified</pose>
		<truncated>0</truncated>
		<difficult>0</difficult>
		<occluded>0</occluded>
		<bndbox>
			<xmin>214</xmin>
			<xmax>242</xmax>
			<ymin>333</ymin>
			<ymax>493</ymax>
		</bndbox>
		<polygon>
			<x1>214.35003</x1>
			<y1>336.464286</y1>
			<x2>213.247369</x2>
			<y2>365.992239</y2>
			<x3>214.68058</x3>
			<y3>429.523817</y3>
			<x4>215.397213</x4>
			<y4>488.058551</y4>
			<x5>225.071525</x5>
			<y5>491.627741</y5>
			<x6>230.804452</x6>
			<y6>435.948372</y6>
			<x7>241.195396</x7>
			<y7>350.287795</y7>
			<x8>234.387534</x8>
			<y8>331.728028</y8>
			<x9>214.35003</x9>
			<y9>336.464286</y9>
		</polygon>
	</object>
	<object>
		<name>RMD</name>
		<pose>Unspecified</pose>
		<truncated>0</truncated>
		<difficult>0</difficult>
		<occluded>0</occluded>
		<bndbox>
			<xmin>132</xmin>
			<xmax>197</xmax>
			<ymin>278</ymin>
			<ymax>416</ymax>
		</bndbox>
		<polygon>
			<x1>131.194773</x1>
			<y1>386.693529</y1>
			<x2>148.751883</x2>
			<y2>414.533228</y2>
			<x3>192.107176</x3>
			<y3>341.007891</y3>
			<x4>196.406865</x4>
			<y4>315.309729</y4>
			<x5>162.36758</x5>
			<y5>277.476299</y5>
			<x6>147.676947</x6>
			<y6>341.007891</y6>
			<x7>137.300965</x7>
			<y7>370.392858</y7>
			<x8>131.194773</x8>
			<y8>386.693529</y8>
		</polygon>
	</object>
	<object>
		<name>LID</name>
		<pose>Unspecified</pose>
		<truncated>0</truncated>
		<difficult>0</difficult>
		<occluded>0</occluded>
		<bndbox>
			<xmin>307</xmin>
			<xmax>328</xmax>
			<ymin>334</ymin>
			<ymax>461</ymax>
		</bndbox>
		<polygon>
			<x1>305.613124</x1>
			<y1>457.363516</y1>
			<x2>320.662087</x2>
			<y2>459.505025</y2>
			<x3>323.886867</x3>
			<y3>394.545765</y3>
			<x4>326.787911</x4>
			<y4>332.892858</y4>
			<x5>307.404665</x5>
			<y5>335.297219</y5>
			<x6>307.762995</x6>
			<y6>393.118084</y6>
			<x7>305.613124</x7>
			<y7>457.363516</y7>
		</polygon>
	</object>
	<object>
		<name>LID</name>
		<pose>Unspecified</pose>
		<truncated>0</truncated>
		<difficult>0</difficult>
		<occluded>0</occluded>
		<bndbox>
			<xmin>323</xmin>
			<xmax>345</xmax>
			<ymin>336</ymin>
			<ymax>456</ymax>
		</bndbox>
		<polygon>
			<x1>322.095325</x1>
			<y1>453.080498</y1>
			<x2>334.994417</x2>
			<y2>454.508153</y2>
			<x3>339.652408</x3>
			<y3>391.690402</y3>
			<x4>343.810379</x4>
			<y4>334.678572</y4>
			<x5>325.678408</x5>
			<y5>336.724873</y5>
			<x6>326.036711</x6>
			<y6>388.835066</y6>
			<x7>322.095325</x7>
			<y7>453.080498</y7>
		</polygon>
	</object>
	<object>
		<name>LCD</name>
		<pose>Unspecified</pose>
		<truncated>0</truncated>
		<difficult>0</difficult>
		<occluded>0</occluded>
		<bndbox>
			<xmin>340</xmin>
			<xmax>364</xmax>
			<ymin>331</ymin>
			<ymax>461</ymax>
		</bndbox>
		<polygon>
			<x1>338.5775</x1>
			<y1>460.218879</y1>
			<x2>348.610114</x2>
			<y2>459.505025</y2>
			<x3>356.492912</x3>
			<y3>400.970292</y3>
			<x4>362.624686</x4>
			<y4>340.035715</y4>
			<x5>345.027032</x5>
			<y5>330.300319</y5>
			<x6>342.518885</x6>
			<y6>395.973447</y6>
			<x7>338.5775</x7>
			<y7>460.218879</y7>
		</polygon>
	</object>
	<object>
		<name>LPMD</name>
		<pose>Unspecified</pose>
		<truncated>0</truncated>
		<difficult>0</difficult>
		<occluded>0</occluded>
		<bndbox>
			<xmin>359</xmin>
			<xmax>384</xmax>
			<ymin>322</ymin>
			<ymax>496</ymax>
		</bndbox>
		<polygon>
			<x1>382.649399</x1>
			<y1>383.838193</y1>
			<x2>383.230831</x2>
			<y2>334.678572</y2>
			<x3>367.600463</x3>
			<y3>321.020456</y3>
			<x4>362.225839</x4>
			<y4>341.007891</y4>
			<x5>360.434298</x5>
			<y5>379.555148</y5>
			<x6>358.284454</x6>
			<y6>452.366644</y6>
			<x7>363.300775</x7>
			<y7>495.196932</y7>
			<x8>375.124931</x8>
			<y8>473.067961</y8>
			<x9>382.649399</x9>
			<y9>383.838193</y9>
		</polygon>
	</object>
	<object>
		<name>LPMD</name>
		<pose>Unspecified</pose>
		<truncated>0</truncated>
		<difficult>0</difficult>
		<occluded>0</occluded>
		<bndbox>
			<xmin>384</xmin>
			<xmax>410</xmax>
			<ymin>330</ymin>
			<ymax>493</ymax>
		</bndbox>
		<polygon>
			<x1>394.473582</x1>
			<y1>328.872651</y1>
			<x2>383.007729</x2>
			<y2>347.432445</y2>
			<x3>385.874178</x3>
			<y3>410.25021</y3>
			<x4>389.815564</x4>
			<y4>492.341596</y4>
			<x5>400.206508</x5>
			<y5>488.058551</y5>
			<x6>408.805912</x6>
			<y6>355.284654</y6>
			<x7>404.284936</x7>
			<y7>331.107144</y7>
			<x8>394.473582</x8>
			<y8>328.872651</y8>
		</polygon>
	</object>
	<object>
		<name>LMD</name>
		<pose>Unspecified</pose>
		<truncated>0</truncated>
		<difficult>0</difficult>
		<occluded>0</occluded>
		<bndbox>
			<xmin>409</xmin>
			<xmax>435</xmax>
			<ymin>321</ymin>
			<ymax>470</ymax>
		</bndbox>
		<polygon>
			<x1>434.245793</x1>
			<y1>363.136876</y1>
			<x2>431.610477</x2>
			<y2>320.392858</y2>
			<x3>408.089307</x3>
			<y3>324.589647</y3>
			<x4>408.447609</x4>
			<y4>346.004791</y4>
			<x5>410.955756</x5>
			<y5>389.548892</y5>
			<x6>415.613774</x6>
			<y6>439.517562</y6>
			<x7>423.138242</x7>
			<y7>469.49877</y7>
			<x8>430.304435</x8>
			<y8>463.074216</y8>
			<x9>434.245793</x9>
			<y9>363.136876</y9>
		</polygon>
	</object>
	<object>
		<name>LMD</name>
		<pose>Unspecified</pose>
		<truncated>0</truncated>
		<difficult>0</difficult>
		<occluded>0</occluded>
		<bndbox>
			<xmin>431</xmin>
			<xmax>498</xmax>
			<ymin>292</ymin>
			<ymax>425</ymax>
		</bndbox>
		<polygon>
			<x1>476.884508</x1>
			<y1>326.017301</y1>
			<x2>461.175816</x2>
			<y2>290.928572</y2>
			<x3>448.936453</x3>
			<y3>312.454379</y3>
			<x4>436.037334</x4>
			<y4>311.026698</y4>
			<x5>429.946105</x5>
			<y5>344.577082</y5>
			<x6>454.669352</x6>
			<y6>383.838193</y6>
			<x7>480.467591</x7>
			<y7>423.813118</y7>
			<x8>496.591462</x8>
			<y8>394.545765</y8>
			<x9>476.884508</x9>
			<y9>326.017301</y9>
		</polygon>
	</object>
</annotation>
