<annotation>
	<folder></folder>
	<filename>185_jpg.rf.7784afb464ee2464512b7071f24af7f2.jpg</filename>
	<path>185_jpg.rf.7784afb464ee2464512b7071f24af7f2.jpg</path>
	<source>
		<database>roboflow.com</database>
	</source>
	<size>
		<width>640</width>
		<height>640</height>
		<depth>3</depth>
	</size>
	<segmented>0</segmented>
	<object>
		<name>RIU</name>
		<pose>Unspecified</pose>
		<truncated>0</truncated>
		<difficult>0</difficult>
		<occluded>0</occluded>
		<bndbox>
			<xmin>284</xmin>
			<xmax>312</xmax>
			<ymin>234</ymin>
			<ymax>370</ymax>
		</bndbox>
		<polygon>
			<x1>310.920165</x1>
			<y1>233.302171</y1>
			<x2>284.661005</x2>
			<y2>235.176015</y2>
			<x3>283.278966</x3>
			<y3>312.627439</y3>
			<x4>287.079626</x4>
			<y4>368.842193</y4>
			<x5>310.920165</x5>
			<y5>368.842193</y5>
			<x6>311.265675</x6>
			<y6>324.495008</y6>
			<x7>310.574629</x7>
			<y7>248.292781</y7>
			<x8>310.920165</x8>
			<y8>233.302171</y8>
		</polygon>
	</object>
	<object>
		<name>RIU</name>
		<pose>Unspecified</pose>
		<truncated>0</truncated>
		<difficult>0</difficult>
		<occluded>0</occluded>
		<bndbox>
			<xmin>261</xmin>
			<xmax>285</xmax>
			<ymin>242</ymin>
			<ymax>376</ymax>
		</bndbox>
		<polygon>
			<x1>262.202531</x1>
			<y1>337.611774</y1>
			<x2>262.548067</x2>
			<y2>375.088276</y2>
			<x3>284.315495</x3>
			<y3>370.716012</y3>
			<x4>281.205855</x4>
			<y4>291.390768</y4>
			<x5>280.514835</x5>
			<y5>240.797476</y5>
			<x6>261.881202</x6>
			<y6>244.812501</y6>
			<x7>260.474956</x7>
			<y7>295.138409</y7>
			<x8>262.202531</x8>
			<y8>337.611774</y8>
		</polygon>
	</object>
	<object>
		<name>RCU</name>
		<pose>Unspecified</pose>
		<truncated>0</truncated>
		<difficult>0</difficult>
		<occluded>0</occluded>
		<bndbox>
			<xmin>236</xmin>
			<xmax>265</xmax>
			<ymin>222</ymin>
			<ymax>374</ymax>
		</bndbox>
		<polygon>
			<x1>242.442757</x1>
			<y1>221.375001</y1>
			<x2>238.362018</x2>
			<y2>278.898601</y2>
			<x3>238.362018</x3>
			<y3>327.618049</y3>
			<x4>235.252378</x4>
			<y4>354.476252</y4>
			<x5>248.036422</x5>
			<y5>372.589857</y5>
			<x6>261.511511</x6>
			<y6>354.476252</y6>
			<x7>263.930106</x7>
			<y7>325.744229</y7>
			<x8>261.511511</x8>
			<y8>223.308446</y8>
			<x9>242.442757</x9>
			<y9>221.375001</y9>
		</polygon>
	</object>
	<object>
		<name>RPMU</name>
		<pose>Unspecified</pose>
		<truncated>0</truncated>
		<difficult>0</difficult>
		<occluded>0</occluded>
		<bndbox>
			<xmin>213</xmin>
			<xmax>244</xmax>
			<ymin>237</ymin>
			<ymax>358</ymax>
		</bndbox>
		<polygon>
			<x1>211.757348</x1>
			<y1>345.731677</y1>
			<x2>224.541418</x2>
			<y2>356.974648</y2>
			<x3>238.362018</x3>
			<y3>348.230168</y3>
			<x4>243.199207</x4>
			<y4>335.738001</y4>
			<x5>240.089593</x5>
			<y5>236.425212</y5>
			<x6>216.956796</x6>
			<y6>237.000001</y6>
			<x7>218.667648</x7>
			<y7>300.135271</y7>
			<x8>211.757348</x8>
			<y8>345.731677</y8>
		</polygon>
	</object>
	<object>
		<name>RPMU</name>
		<pose>Unspecified</pose>
		<truncated>0</truncated>
		<difficult>0</difficult>
		<occluded>0</occluded>
		<bndbox>
			<xmin>174</xmin>
			<xmax>217</xmax>
			<ymin>237</ymin>
			<ymax>349</ymax>
		</bndbox>
		<polygon>
			<x1>186.189247</x1>
			<y1>348.230168</y1>
			<x2>198.282258</x2>
			<y2>338.236396</y2>
			<x3>209.684263</x3>
			<y3>340.110217</y3>
			<x4>215.903543</x4>
			<y4>315.750481</y4>
			<x5>205.192558</x5>
			<y5>284.520062</y5>
			<x6>196.222454</x6>
			<y6>239.343751</y6>
			<x7>196.209174</x7>
			<y7>237.049835</y7>
			<x8>173.40519</x8>
			<y8>236.425212</y8>
			<x9>178.242392</x9>
			<y9>291.390768</y9>
			<x10>179.969967</x10>
			<y10>334.488732</y10>
			<x11>186.189247</x11>
			<y11>348.230168</y11>
		</polygon>
	</object>
	<object>
		<name>RMU</name>
		<pose>Unspecified</pose>
		<truncated>0</truncated>
		<difficult>0</difficult>
		<occluded>0</occluded>
		<bndbox>
			<xmin>150</xmin>
			<xmax>181</xmax>
			<ymin>214</ymin>
			<ymax>352</ymax>
		</bndbox>
		<polygon>
			<x1>154.321806</x1>
			<y1>213.562501</y1>
			<x2>153.0198</x2>
			<y2>268.280254</y2>
			<x3>153.710833</x3>
			<y3>313.87666</y3>
			<x4>149.219141</x4>
			<y4>334.488732</y4>
			<x5>169.95004</x5>
			<y5>350.728564</y5>
			<x6>179.278947</x6>
			<y6>336.362576</y6>
			<x7>179.624457</x7>
			<y7>290.141547</y7>
			<x8>173.059667</x8>
			<y8>213.314734</y8>
			<x9>154.321806</x9>
			<y9>213.562501</y9>
		</polygon>
	</object>
	<object>
		<name>RMU</name>
		<pose>Unspecified</pose>
		<truncated>0</truncated>
		<difficult>0</difficult>
		<occluded>0</occluded>
		<bndbox>
			<xmin>124</xmin>
			<xmax>155</xmax>
			<ymin>214</ymin>
			<ymax>337</ymax>
		</bndbox>
		<polygon>
			<x1>122.959994</x1>
			<y1>311.378218</y1>
			<x2>137.471626</x2>
			<y2>336.362576</y2>
			<x3>151.637748</x3>
			<y3>329.491917</y3>
			<x4>154.401865</x4>
			<y4>298.261451</y4>
			<x5>149.219141</x5>
			<y5>217.062363</y5>
			<x6>130.995672</x6>
			<y6>212.781251</y6>
			<x7>132.288901</x7>
			<y7>270.154074</y7>
			<x8>122.959994</x8>
			<y8>311.378218</y8>
		</polygon>
	</object>
	<object>
		<name>LIU</name>
		<pose>Unspecified</pose>
		<truncated>0</truncated>
		<difficult>0</difficult>
		<occluded>0</occluded>
		<bndbox>
			<xmin>316</xmin>
			<xmax>343</xmax>
			<ymin>241</ymin>
			<ymax>375</ymax>
		</bndbox>
		<polygon>
			<x1>316.107192</x1>
			<y1>363.220731</y1>
			<x2>333.728451</x2>
			<y2>374.463677</y2>
			<x3>342.366326</x3>
			<y3>335.113354</y3>
			<x4>341.794808</x4>
			<y4>246.375001</y4>
			<x5>316.452702</x5>
			<y5>240.172877</y5>
			<x6>314.725127</x6>
			<y6>303.882936</y6>
			<x7>316.107192</x7>
			<y7>363.220731</y7>
		</polygon>
	</object>
	<object>
		<name>LIU</name>
		<pose>Unspecified</pose>
		<truncated>0</truncated>
		<difficult>0</difficult>
		<occluded>0</occluded>
		<bndbox>
			<xmin>341</xmin>
			<xmax>370</xmax>
			<ymin>251</ymin>
			<ymax>380</ymax>
		</bndbox>
		<polygon>
			<x1>367.243395</x1>
			<y1>309.504397</y1>
			<x2>362.097184</x2>
			<y2>263.562501</y2>
			<x3>361.36965</x3>
			<y3>250.166601</y3>
			<x4>342.366326</x4>
			<y4>253.914266</y4>
			<x5>340.293241</x5>
			<y5>333.239534</y5>
			<x6>343.402855</x6>
			<y6>370.716012</y6>
			<x7>354.80486</x7>
			<y7>378.835941</y7>
			<x8>368.62546</x8>
			<y8>366.343773</y8>
			<x9>367.243395</x9>
			<y9>309.504397</y9>
		</polygon>
	</object>
	<object>
		<name>LCU</name>
		<pose>Unspecified</pose>
		<truncated>0</truncated>
		<difficult>0</difficult>
		<occluded>0</occluded>
		<bndbox>
			<xmin>367</xmin>
			<xmax>399</xmax>
			<ymin>241</ymin>
			<ymax>377</ymax>
		</bndbox>
		<polygon>
			<x1>366.206865</x1>
			<y1>239.548254</y1>
			<x2>366.206865</x2>
			<y2>330.741091</y2>
			<x3>369.662015</x3>
			<y3>365.719151</y3>
			<x4>381.409504</x4>
			<y4>375.712899</y4>
			<x5>397.648724</x5>
			<y5>361.971509</y5>
			<x6>389.701869</x6>
			<y6>302.009092</y6>
			<x7>387.583145</x7>
			<y7>244.031251</y7>
			<x8>366.206865</x8>
			<y8>239.548254</y8>
		</polygon>
	</object>
	<object>
		<name>LPMU</name>
		<pose>Unspecified</pose>
		<truncated>0</truncated>
		<difficult>0</difficult>
		<occluded>0</occluded>
		<bndbox>
			<xmin>394</xmin>
			<xmax>440</xmax>
			<ymin>217</ymin>
			<ymax>356</ymax>
		</bndbox>
		<polygon>
			<x1>392.811509</x1>
			<y1>318.873523</y1>
			<x2>399.030789</x2>
			<y2>348.230168</y2>
			<x3>414.578963</x3>
			<y3>355.100803</y3>
			<x4>422.525792</x4>
			<y4>308.255176</y4>
			<x5>438.765013</x5>
			<y5>220.185404</y5>
			<x6>420.844484</x6>
			<y6>215.906251</y6>
			<x7>403.176958</x7>
			<y7>287.018505</y7>
			<x8>392.811509</x8>
			<y8>318.873523</y8>
		</polygon>
	</object>
	<object>
		<name>LPMU</name>
		<pose>Unspecified</pose>
		<truncated>0</truncated>
		<difficult>0</difficult>
		<occluded>0</occluded>
		<bndbox>
			<xmin>412</xmin>
			<xmax>468</xmax>
			<ymin>209</ymin>
			<ymax>360</ymax>
		</bndbox>
		<polygon>
			<x1>451.549083</x1>
			<y1>300.135271</y1>
			<x2>467.064787</x2>
			<y2>216.687501</y2>
			<x3>439.110522</x3>
			<y3>207.693237</y3>
			<x4>417.688577</x4>
			<y4>298.88605</y4>
			<x5>410.778277</x5>
			<y5>337.611774</y5>
			<x6>422.871302</x6>
			<y6>353.851606</y6>
			<x7>440.147051</x7>
			<y7>358.848467</y7>
			<x8>448.784952</x8>
			<y8>354.476252</y8>
			<x9>451.549083</x9>
			<y9>300.135271</y9>
		</polygon>
	</object>
	<object>
		<name>LMU</name>
		<pose>Unspecified</pose>
		<truncated>0</truncated>
		<difficult>0</difficult>
		<occluded>0</occluded>
		<bndbox>
			<xmin>451</xmin>
			<xmax>485</xmax>
			<ymin>217</ymin>
			<ymax>352</ymax>
		</bndbox>
		<polygon>
			<x1>478.153726</x1>
			<y1>285.769284</y1>
			<x2>483.911439</x2>
			<y2>215.906251</y2>
			<x3>466.751721</x3>
			<y3>215.813141</y3>
			<x4>450.512527</x4>
			<y4>299.510672</y4>
			<x5>449.821508</x5>
			<y5>333.239534</y5>
			<x6>454.658697</x6>
			<y6>348.854719</y6>
			<x7>472.971001</x7>
			<y7>350.728564</y7>
			<x8>483.681934</x8>
			<y8>329.491917</y8>
			<x9>478.153726</x9>
			<y9>285.769284</y9>
		</polygon>
	</object>
	<object>
		<name>LMU</name>
		<pose>Unspecified</pose>
		<truncated>0</truncated>
		<difficult>0</difficult>
		<occluded>0</occluded>
		<bndbox>
			<xmin>478</xmin>
			<xmax>514</xmax>
			<ymin>211</ymin>
			<ymax>331</ymax>
		</bndbox>
		<polygon>
			<x1>482.645431</x1>
			<y1>212.065489</y1>
			<x2>477.462707</x2>
			<y2>300.759894</y2>
			<x3>481.608876</x3>
			<y3>325.744229</y3>
			<x4>491.283306</x4>
			<y4>330.116493</y4>
			<x5>513.396244</x5>
			<y5>307.630576</y5>
			<x6>502.685259</x6>
			<y6>272.027894</y6>
			<x7>504.213815</x7>
			<y7>210.437501</y7>
			<x8>482.645431</x8>
			<y8>212.065489</y8>
		</polygon>
	</object>
	<object>
		<name>RID</name>
		<pose>Unspecified</pose>
		<truncated>0</truncated>
		<difficult>0</difficult>
		<occluded>0</occluded>
		<bndbox>
			<xmin>291</xmin>
			<xmax>313</xmax>
			<ymin>382</ymin>
			<ymax>502</ymax>
		</bndbox>
		<polygon>
			<x1>290.617215</x1>
			<y1>496.669626</y1>
			<x2>311.693624</x2>
			<y2>501.041843</y2>
			<x3>306.856409</x3>
			<y3>455.445436</y3>
			<x4>310.261331</x4>
			<y4>380.750001</y4>
			<x5>289.58066</x5>
			<y5>386.738515</y5>
			<x6>290.617215</x6>
			<y6>437.956383</y6>
			<x7>290.617215</x7>
			<y7>496.669626</y7>
		</polygon>
	</object>
	<object>
		<name>RID</name>
		<pose>Unspecified</pose>
		<truncated>0</truncated>
		<difficult>0</difficult>
		<occluded>0</occluded>
		<bndbox>
			<xmin>268</xmin>
			<xmax>291</xmax>
			<ymin>388</ymin>
			<ymax>544</ymax>
		</bndbox>
		<polygon>
			<x1>288.88964</x1>
			<y1>474.183687</y1>
			<x2>290.271679</x2>
			<y2>386.738515</y2>
			<x3>267.496752</x3>
			<y3>387.000001</y3>
			<x4>267.467696</x4>
			<y4>428.587257</y4>
			<x5>269.19527</x5>
			<y5>520.404693</y5>
			<x6>283.706916</x6>
			<y6>542.890608</y6>
			<x7>288.88964</x7>
			<y7>474.183687</y7>
		</polygon>
	</object>
	<object>
		<name>RCD</name>
		<pose>Unspecified</pose>
		<truncated>0</truncated>
		<difficult>0</difficult>
		<occluded>0</occluded>
		<bndbox>
			<xmin>241</xmin>
			<xmax>269</xmax>
			<ymin>376</ymin>
			<ymax>542</ymax>
		</bndbox>
		<polygon>
			<x1>247.194377</x1>
			<y1>376.843751</y1>
			<x2>242.245117</x2>
			<y2>406.101365</y2>
			<x3>240.517542</x3>
			<y3>472.309843</y3>
			<x4>240.172006</x4>
			<y4>507.912525</y4>
			<x5>258.484311</x5>
			<y5>541.016764</y5>
			<x6>264.012546</x6>
			<y6>478.555926</y6>
			<x7>268.158741</x7>
			<y7>392.984599</y7>
			<x8>250.191946</x8>
			<y8>374.870946</y8>
			<x9>247.194377</x9>
			<y9>376.843751</y9>
		</polygon>
	</object>
	<object>
		<name>RPMD</name>
		<pose>Unspecified</pose>
		<truncated>0</truncated>
		<difficult>0</difficult>
		<occluded>0</occluded>
		<bndbox>
			<xmin>216</xmin>
			<xmax>247</xmax>
			<ymin>372</ymin>
			<ymax>514</ymax>
		</bndbox>
		<polygon>
			<x1>220.844484</x1>
			<y1>371.375001</y1>
			<x2>218.404578</x2>
			<y2>401.104502</y2>
			<x3>214.949428</x3>
			<y3>471.060645</y3>
			<x4>217.022513</x4>
			<y4>512.909387</y4>
			<x5>227.387962</x5>
			<y5>506.038752</y5>
			<x6>238.444431</x6>
			<y6>432.334921</y6>
			<x7>245.700267</x7>
			<y7>392.984599</y7>
			<x8>234.989281</x8>
			<y8>373.621725</y8>
			<x9>220.844484</x9>
			<y9>371.375001</y9>
		</polygon>
	</object>
	<object>
		<name>RPMD</name>
		<pose>Unspecified</pose>
		<truncated>0</truncated>
		<difficult>0</difficult>
		<occluded>0</occluded>
		<bndbox>
			<xmin>193</xmin>
			<xmax>222</xmax>
			<ymin>370</ymin>
			<ymax>510</ymax>
		</bndbox>
		<polygon>
			<x1>211.839788</x1>
			<y1>369.249473</y1>
			<x2>194.926558</x2>
			<y2>379.968751</y2>
			<x3>191.799908</x3>
			<y3>434.208742</y3>
			<x4>191.799908</x4>
			<y4>500.417219</y4>
			<x5>199.401254</x5>
			<y5>509.161794</y5>
			<x6>206.657063</x6>
			<y6>497.918801</y6>
			<x7>210.803232</x7>
			<y7>437.331784</y7>
			<x8>221.168682</x8>
			<y8>381.741629</y8>
			<x9>211.839788</x9>
			<y9>369.249473</y9>
		</polygon>
	</object>
	<object>
		<name>RMD</name>
		<pose>Unspecified</pose>
		<truncated>0</truncated>
		<difficult>0</difficult>
		<occluded>0</occluded>
		<bndbox>
			<xmin>134</xmin>
			<xmax>184</xmax>
			<ymin>358</ymin>
			<ymax>455</ymax>
		</bndbox>
		<polygon>
			<x1>183.162034</x1>
			<y1>382.366251</y1>
			<x2>161.740115</x2>
			<y2>357.381905</y2>
			<x3>148.265025</x3>
			<y3>359.880348</y3>
			<x4>132.723534</x4>
			<y4>404.968751</y4>
			<x5>151.374665</x5>
			<y5>454.196214</y5>
			<x6>176.251734</x6>
			<y6>414.845892</y6>
			<x7>183.162034</x7>
			<y7>382.366251</y7>
		</polygon>
	</object>
	<object>
		<name>LID</name>
		<pose>Unspecified</pose>
		<truncated>0</truncated>
		<difficult>0</difficult>
		<occluded>0</occluded>
		<bndbox>
			<xmin>310</xmin>
			<xmax>330</xmax>
			<ymin>387</ymin>
			<ymax>486</ymax>
		</bndbox>
		<polygon>
			<x1>315.494284</x1>
			<y1>484.802034</y1>
			<x2>329.314883</x2>
			<y2>485.426633</y2>
			<x3>328.623864</x3>
			<y3>451.697771</y3>
			<x4>326.244053</x4>
			<y4>386.218751</y4>
			<x5>308.929494</x5>
			<y5>386.738515</y5>
			<x6>309.966049</x6>
			<y6>439.830226</y6>
			<x7>315.494284</x7>
			<y7>484.802034</y7>
		</polygon>
	</object>
	<object>
		<name>LID</name>
		<pose>Unspecified</pose>
		<truncated>0</truncated>
		<difficult>0</difficult>
		<occluded>0</occluded>
		<bndbox>
			<xmin>327</xmin>
			<xmax>352</xmax>
			<ymin>382</ymin>
			<ymax>511</ymax>
		</bndbox>
		<polygon>
			<x1>325.859734</x1>
			<y1>381.11703</y1>
			<x2>326.896289</x2>
			<y2>409.224407</y2>
			<x3>330.351439</x3>
			<y3>471.060645</y3>
			<x4>331.733478</x4>
			<y4>509.786345</y4>
			<x5>351.427848</x5>
			<y5>507.912525</y5>
			<x6>350.391292</x6>
			<y6>429.211879</y6>
			<x7>350.434117</x7>
			<y7>383.875001</y7>
			<x8>325.859734</x8>
			<y8>381.11703</y8>
		</polygon>
	</object>
	<object>
		<name>LCD</name>
		<pose>Unspecified</pose>
		<truncated>0</truncated>
		<difficult>0</difficult>
		<occluded>0</occluded>
		<bndbox>
			<xmin>351</xmin>
			<xmax>383</xmax>
			<ymin>376</ymin>
			<ymax>513</ymax>
		</bndbox>
		<polygon>
			<x1>349.700273</x1>
			<y1>385.489293</y1>
			<x2>353.155423</x2>
			<y2>437.956383</y2>
			<x3>355.919527</x3>
			<y3>496.669626</y3>
			<x4>366.630512</x4>
			<y4>512.284836</y4>
			<x5>381.833151</x5>
			<y5>498.543399</y5>
			<x6>378.378001</x6>
			<y6>436.082562</y6>
			<x7>374.624182</x7>
			<y7>375.281251</y7>
			<x8>349.700273</x8>
			<y8>385.489293</y8>
		</polygon>
	</object>
	<object>
		<name>LPMD</name>
		<pose>Unspecified</pose>
		<truncated>0</truncated>
		<difficult>0</difficult>
		<occluded>0</occluded>
		<bndbox>
			<xmin>379</xmin>
			<xmax>405</xmax>
			<ymin>377</ymin>
			<ymax>513</ymax>
		</bndbox>
		<polygon>
			<x1>403.946115</x1>
			<y1>415.470491</y1>
			<x2>403.997832</x2>
			<y2>376.062501</y2>
			<x3>377.686982</x3>
			<y3>386.113893</y3>
			<x4>380.105576</x4>
			<y4>465.43916</y4>
			<x5>388.743451</x5>
			<y5>504.164884</y5>
			<x6>398.072371</x6>
			<y6>512.284836</y6>
			<x7>403.600632</x7>
			<y7>506.663303</y7>
			<x8>400.836501</x8>
			<y8>466.063759</y8>
			<x9>403.946115</x9>
			<y9>415.470491</y9>
		</polygon>
	</object>
	<object>
		<name>LPMD</name>
		<pose>Unspecified</pose>
		<truncated>0</truncated>
		<difficult>0</difficult>
		<occluded>0</occluded>
		<bndbox>
			<xmin>401</xmin>
			<xmax>431</xmax>
			<ymin>373</ymin>
			<ymax>520</ymax>
		</bndbox>
		<polygon>
			<x1>419.148806</x1>
			<y1>518.530919</y1>
			<x2>424.331531</x2>
			<y2>488.549675</y2>
			<x3>425.02255</x3>
			<y3>426.713436</y3>
			<x4>429.915759</x4>
			<y4>387.781251</y4>
			<x5>413.620545</x5>
			<y5>372.372515</y5>
			<x6>400.490965</x6>
			<y6>389.861557</y6>
			<x7>405.328207</x7>
			<y7>414.845892</y7>
			<x8>402.564076</x8>
			<y8>467.937603</y8>
			<x9>404.637135</x9>
			<y9>511.660189</y9>
			<x10>419.148806</x10>
			<y10>518.530919</y10>
		</polygon>
	</object>
	<object>
		<name>LMD</name>
		<pose>Unspecified</pose>
		<truncated>0</truncated>
		<difficult>0</difficult>
		<occluded>0</occluded>
		<bndbox>
			<xmin>432</xmin>
			<xmax>497</xmax>
			<ymin>361</ymin>
			<ymax>488</ymax>
		</bndbox>
		<polygon>
			<x1>430.896294</x1>
			<y1>397.356838</y1>
			<x2>453.700305</x2>
			<y2>444.827089</y2>
			<x3>482.723542</x3>
			<y3>486.675854</y3>
			<x4>493.780011</x4>
			<y4>476.682106</y4>
			<x5>496.198606</x5>
			<y5>443.577868</y5>
			<x6>474.776687</x6>
			<y6>392.359976</y6>
			<x7>465.768891</x7>
			<y7>359.656251</y7>
			<x8>430.896294</x8>
			<y8>397.356838</y8>
		</polygon>
	</object>
	<object>
		<name>LMD</name>
		<pose>Unspecified</pose>
		<truncated>0</truncated>
		<difficult>0</difficult>
		<occluded>0</occluded>
		<bndbox>
			<xmin>469</xmin>
			<xmax>524</xmax>
			<ymin>338</ymin>
			<ymax>457</ymax>
		</bndbox>
		<polygon>
			<x1>468.211924</x1>
			<y1>361.129558</y1>
			<x2>476.504262</x2>
			<y2>404.227544</y2>
			<x3>502.417886</x3>
			<y3>452.946992</y3>
			<x4>523.148785</x4>
			<y4>456.070034</y4>
			<x5>519.002616</x5>
			<y5>402.353724</y5>
			<x6>507.237573</x6>
			<y6>376.062501</y6>
			<x7>498.271717</x7>
			<y7>336.769857</y7>
			<x8>468.211924</x8>
			<y8>361.129558</y8>
		</polygon>
	</object>
</annotation>
