<annotation>
	<folder></folder>
	<filename>65_jpg.rf.2c867df49c972c326f8a47826d82c07a.jpg</filename>
	<path>65_jpg.rf.2c867df49c972c326f8a47826d82c07a.jpg</path>
	<source>
		<database>roboflow.com</database>
	</source>
	<size>
		<width>640</width>
		<height>640</height>
		<depth>3</depth>
	</size>
	<segmented>0</segmented>
	<object>
		<name>RPMU</name>
		<pose>Unspecified</pose>
		<truncated>0</truncated>
		<difficult>0</difficult>
		<occluded>0</occluded>
		<bndbox>
			<xmin>206</xmin>
			<xmax>230</xmax>
			<ymin>200</ymin>
			<ymax>350</ymax>
		</bndbox>
		<polygon>
			<x1>208.720235</x1>
			<y1>346.75</y1>
			<x2>223.771681</x2>
			<y2>349.25</y2>
			<x3>228.788829</x3>
			<y3>346.75</y3>
			<x4>228.161685</x4>
			<y4>314.25</y4>
			<x5>226.907398</x5>
			<y5>286.75</y5>
			<x6>224.398824</x6>
			<y6>263</y6>
			<x7>218.754532</x7>
			<y7>223</y7>
			<x8>213.11024</x8>
			<y8>199.25</y8>
			<x9>204.957374</x9>
			<y9>216.75</y9>
			<x10>208.720235</x10>
			<y10>244.25</y10>
			<x11>209.347379</x11>
			<y11>288</y11>
			<x12>205.584517</x12>
			<y12>319.25</y12>
			<x13>208.720235</x13>
			<y13>346.75</y13>
		</polygon>
	</object>
	<object>
		<name>RPMU</name>
		<pose>Unspecified</pose>
		<truncated>0</truncated>
		<difficult>0</difficult>
		<occluded>0</occluded>
		<bndbox>
			<xmin>227</xmin>
			<xmax>252</xmax>
			<ymin>205</ymin>
			<ymax>358</ymax>
		</bndbox>
		<polygon>
			<x1>248.857423</x1>
			<y1>349.25</y1>
			<x2>250.738854</x2>
			<y2>311.75</y2>
			<x3>245.721705</x3>
			<y3>275.5</y3>
			<x4>244.467418</x4>
			<y4>241.75</y4>
			<x5>238.823126</x5>
			<y5>211.75</y5>
			<x6>234.433121</x6>
			<y6>204.25</y6>
			<x7>230.67026</x7>
			<y7>209.25</y7>
			<x8>231.297403</x8>
			<y8>264.25</y8>
			<x9>230.67026</x9>
			<y9>314.25</y9>
			<x10>225.653111</x10>
			<y10>341.75</y10>
			<x11>238.195982</x11>
			<y11>356.75</y11>
			<x12>248.857423</x12>
			<y12>349.25</y12>
		</polygon>
	</object>
	<object>
		<name>RCU</name>
		<pose>Unspecified</pose>
		<truncated>0</truncated>
		<difficult>0</difficult>
		<occluded>0</occluded>
		<bndbox>
			<xmin>244</xmin>
			<xmax>274</xmax>
			<ymin>197</ymin>
			<ymax>368</ymax>
		</bndbox>
		<polygon>
			<x1>243.213131</x1>
			<y1>205.5</y1>
			<x2>250.11171</x2>
			<y2>313</y2>
			<x3>247.603136</x3>
			<y3>354.25</y3>
			<x4>257.637433</x4>
			<y4>366.75</y4>
			<x5>273.316022</x5>
			<y5>358</y5>
			<x6>272.061734</x6>
			<y6>311.75</y6>
			<x7>269.55316</x7>
			<y7>235.5</y7>
			<x8>251.365997</x8>
			<y8>195.5</y8>
			<x9>243.213131</x9>
			<y9>205.5</y9>
		</polygon>
	</object>
	<object>
		<name>RIU</name>
		<pose>Unspecified</pose>
		<truncated>0</truncated>
		<difficult>0</difficult>
		<occluded>0</occluded>
		<bndbox>
			<xmin>272</xmin>
			<xmax>293</xmax>
			<ymin>214</ymin>
			<ymax>363</ymax>
		</bndbox>
		<polygon>
			<x1>271.434591</x1>
			<y1>223</y1>
			<x2>273.943165</x2>
			<y2>338</y2>
			<x3>280.214601</x3>
			<y3>361.75</y3>
			<x4>291.503185</x4>
			<y4>358</y4>
			<x5>290.876041</x5>
			<y5>308</y5>
			<x6>288.367467</x6>
			<y6>246.75</y6>
			<x7>287.11318</x7>
			<y7>213</y7>
			<x8>273.316022</x8>
			<y8>213</y8>
			<x9>271.434591</x9>
			<y9>223</y9>
		</polygon>
	</object>
	<object>
		<name>RIU</name>
		<pose>Unspecified</pose>
		<truncated>0</truncated>
		<difficult>0</difficult>
		<occluded>0</occluded>
		<bndbox>
			<xmin>292</xmin>
			<xmax>323</xmax>
			<ymin>210</ymin>
			<ymax>370</ymax>
		</bndbox>
		<polygon>
			<x1>291.503185</x1>
			<y1>353</y1>
			<x2>295.89319</x2>
			<y2>369.25</y2>
			<x3>322.233219</x3>
			<y3>361.75</y3>
			<x4>318.470358</x4>
			<y4>304.25</y4>
			<x5>311.571779</x5>
			<y5>209.25</y5>
			<x6>290.876041</x6>
			<y6>229.25</y6>
			<x7>292.130328</x7>
			<y7>304.25</y7>
			<x8>291.503185</x8>
			<y8>353</y8>
		</polygon>
	</object>
	<object>
		<name>RMU</name>
		<pose>Unspecified</pose>
		<truncated>0</truncated>
		<difficult>0</difficult>
		<occluded>0</occluded>
		<bndbox>
			<xmin>155</xmin>
			<xmax>194</xmax>
			<ymin>209</ymin>
			<ymax>333</ymax>
		</bndbox>
		<polygon>
			<x1>177.363057</x1>
			<y1>211.75</y1>
			<x2>157.921607</x2>
			<y2>208</y2>
			<x3>153.531602</x3>
			<y3>221.75</y3>
			<x4>158.548751</x4>
			<y4>279.25</y4>
			<x5>156.66732</x5>
			<y5>306.75</y5>
			<x6>159.175894</x6>
			<y6>331.75</y6>
			<x7>191.160216</x7>
			<y7>330.5</y7>
			<x8>193.041646</x8>
			<y8>299.25</y8>
			<x9>184.261636</x9>
			<y9>251.75</y9>
			<x10>177.363057</x10>
			<y10>211.75</y10>
		</polygon>
	</object>
	<object>
		<name>RMU</name>
		<pose>Unspecified</pose>
		<truncated>0</truncated>
		<difficult>0</difficult>
		<occluded>0</occluded>
		<bndbox>
			<xmin>134</xmin>
			<xmax>158</xmax>
			<ymin>205</ymin>
			<ymax>322</ymax>
		</bndbox>
		<polygon>
			<x1>157.294463</x1>
			<y1>291.75</y1>
			<x2>155.413033</x2>
			<y2>241.75</y2>
			<x3>156.66732</x3>
			<y3>208</y3>
			<x4>134.090152</x4>
			<y4>204.25</y4>
			<x5>136.598726</x5>
			<y5>224.25</y5>
			<x6>134.717295</x6>
			<y6>259.25</y6>
			<x7>133.463008</x7>
			<y7>294.25</y7>
			<x8>137.853013</x8>
			<y8>319.25</y8>
			<x9>154.785889</x9>
			<y9>320.5</y9>
			<x10>157.294463</x10>
			<y10>291.75</y10>
		</polygon>
	</object>
	<object>
		<name>LIU</name>
		<pose>Unspecified</pose>
		<truncated>0</truncated>
		<difficult>0</difficult>
		<occluded>0</occluded>
		<bndbox>
			<xmin>321</xmin>
			<xmax>352</xmax>
			<ymin>207</ymin>
			<ymax>372</ymax>
		</bndbox>
		<polygon>
			<x1>324.11465</x1>
			<y1>223</y1>
			<x2>321.606075</x2>
			<y2>325.5</y2>
			<x3>320.351788</x3>
			<y3>370.5</y3>
			<x4>351.081823</x4>
			<y4>360.5</y4>
			<x5>347.946105</x5>
			<y5>313</y5>
			<x6>344.183244</x6>
			<y6>250.5</y6>
			<x7>342.928956</x7>
			<y7>205.5</y7>
			<x8>322.233219</x8>
			<y8>208</y8>
			<x9>324.11465</x9>
			<y9>223</y9>
		</polygon>
	</object>
	<object>
		<name>LIU</name>
		<pose>Unspecified</pose>
		<truncated>0</truncated>
		<difficult>0</difficult>
		<occluded>0</occluded>
		<bndbox>
			<xmin>351</xmin>
			<xmax>375</xmax>
			<ymin>209</ymin>
			<ymax>352</ymax>
		</bndbox>
		<polygon>
			<x1>351.708966</x1>
			<y1>348</y1>
			<x2>373.658991</x2>
			<y2>350.5</y2>
			<x3>369.268986</x3>
			<y3>304.25</y3>
			<x4>364.251837</x4>
			<y4>240.5</y4>
			<x5>357.980402</x5>
			<y5>208</y5>
			<x6>349.827536</x6>
			<y6>216.75</y6>
			<x7>350.454679</x7>
			<y7>299.25</y7>
			<x8>351.708966</x8>
			<y8>348</y8>
		</polygon>
	</object>
	<object>
		<name>LCU</name>
		<pose>Unspecified</pose>
		<truncated>0</truncated>
		<difficult>0</difficult>
		<occluded>0</occluded>
		<bndbox>
			<xmin>369</xmin>
			<xmax>397</xmax>
			<ymin>199</ymin>
			<ymax>359</ymax>
		</bndbox>
		<polygon>
			<x1>368.014699</x1>
			<y1>206.75</y1>
			<x2>371.150416</x2>
			<y2>311.75</y2>
			<x3>376.167565</x3>
			<y3>358</y3>
			<x4>394.981872</x4>
			<y4>351.75</y4>
			<x5>396.236159</x5>
			<y5>339.25</y5>
			<x6>391.846154</x6>
			<y6>296.75</y6>
			<x7>388.710436</x7>
			<y7>243</y7>
			<x8>386.829005</x8>
			<y8>198</y8>
			<x9>368.014699</x9>
			<y9>206.75</y9>
		</polygon>
	</object>
	<object>
		<name>LPMU</name>
		<pose>Unspecified</pose>
		<truncated>0</truncated>
		<difficult>0</difficult>
		<occluded>0</occluded>
		<bndbox>
			<xmin>396</xmin>
			<xmax>419</xmax>
			<ymin>203</ymin>
			<ymax>359</ymax>
		</bndbox>
		<polygon>
			<x1>402.507594</x1>
			<y1>216.75</y1>
			<x2>394.981872</x2>
			<y2>305.5</y2>
			<x3>394.981872</x3>
			<y3>339.25</y3>
			<x4>410.033317</x4>
			<y4>358</y4>
			<x5>418.186183</x5>
			<y5>338</y5>
			<x6>408.151886</x6>
			<y6>281.75</y6>
			<x7>412.541891</x7>
			<y7>223</y7>
			<x8>413.169035</x8>
			<y8>201.75</y8>
			<x9>402.507594</x9>
			<y9>216.75</y9>
		</polygon>
	</object>
	<object>
		<name>LPMU</name>
		<pose>Unspecified</pose>
		<truncated>0</truncated>
		<difficult>0</difficult>
		<occluded>0</occluded>
		<bndbox>
			<xmin>412</xmin>
			<xmax>441</xmax>
			<ymin>198</ymin>
			<ymax>345</ymax>
		</bndbox>
		<polygon>
			<x1>417.55904</x1>
			<y1>220.5</y1>
			<x2>411.287604</x2>
			<y2>294.25</y2>
			<x3>418.813327</x3>
			<y3>344.25</y3>
			<x4>439.509064</x4>
			<y4>335.5</y4>
			<x5>439.509064</x5>
			<y5>316.75</y5>
			<x6>428.847624</x6>
			<y6>273</y6>
			<x7>433.864772</x7>
			<y7>208</y7>
			<x8>416.931896</x8>
			<y8>196.75</y8>
			<x9>417.55904</x9>
			<y9>220.5</y9>
		</polygon>
	</object>
	<object>
		<name>LMU</name>
		<pose>Unspecified</pose>
		<truncated>0</truncated>
		<difficult>0</difficult>
		<occluded>0</occluded>
		<bndbox>
			<xmin>438</xmin>
			<xmax>478</xmax>
			<ymin>189</ymin>
			<ymax>329</ymax>
		</bndbox>
		<polygon>
			<x1>474.00196</x1>
			<y1>229.25</y1>
			<x2>477.137678</x2>
			<y2>188</y2>
			<x3>460.831945</x3>
			<y3>203</y3>
			<x4>445.153356</x4>
			<y4>248</y4>
			<x5>437.00049</x5>
			<y5>309.25</y5>
			<x6>449.543361</x6>
			<y6>328</y6>
			<x7>468.984811</x7>
			<y7>324.25</y7>
			<x8>473.374816</x8>
			<y8>316.75</y8>
			<x9>472.120529</x9>
			<y9>271.75</y9>
			<x10>474.00196</x10>
			<y10>229.25</y10>
		</polygon>
	</object>
	<object>
		<name>LMU</name>
		<pose>Unspecified</pose>
		<truncated>0</truncated>
		<difficult>0</difficult>
		<occluded>0</occluded>
		<bndbox>
			<xmin>474</xmin>
			<xmax>508</xmax>
			<ymin>193</ymin>
			<ymax>318</ymax>
		</bndbox>
		<polygon>
			<x1>480.273395</x1>
			<y1>203</y1>
			<x2>472.747673</x2>
			<y2>280.5</y2>
			<x3>474.00196</x3>
			<y3>314.25</y3>
			<x4>487.799118</x4>
			<y4>316.75</y4>
			<x5>507.240568</x5>
			<y5>305.5</y5>
			<x6>502.22342</x6>
			<y6>263</y6>
			<x7>493.44341</x7>
			<y7>216.75</y7>
			<x8>490.307692</x8>
			<y8>191.75</y8>
			<x9>480.273395</x9>
			<y9>203</y9>
		</polygon>
	</object>
	<object>
		<name>RCD</name>
		<pose>Unspecified</pose>
		<truncated>0</truncated>
		<difficult>0</difficult>
		<occluded>0</occluded>
		<bndbox>
			<xmin>263</xmin>
			<xmax>286</xmax>
			<ymin>372</ymin>
			<ymax>528</ymax>
		</bndbox>
		<polygon>
			<x1>284.604606</x1>
			<y1>393</y1>
			<x2>282.723175</x2>
			<y2>370.5</y2>
			<x3>262.027438</x3>
			<y3>386.75</y3>
			<x4>263.281725</x4>
			<y4>434.25</y4>
			<x5>262.027438</x5>
			<y5>498</y5>
			<x6>262.654581</x6>
			<y6>526.75</y6>
			<x7>275.824596</x7>
			<y7>523</y7>
			<x8>284.604606</x8>
			<y8>486.75</y8>
			<x9>282.723175</x9>
			<y9>421.75</y9>
			<x10>284.604606</x10>
			<y10>393</y10>
		</polygon>
	</object>
	<object>
		<name>RID</name>
		<pose>Unspecified</pose>
		<truncated>0</truncated>
		<difficult>0</difficult>
		<occluded>0</occluded>
		<bndbox>
			<xmin>285</xmin>
			<xmax>307</xmax>
			<ymin>377</ymin>
			<ymax>505</ymax>
		</bndbox>
		<polygon>
			<x1>283.977462</x1>
			<y1>380.5</y1>
			<x2>285.858893</x2>
			<y2>423</y2>
			<x3>290.248898</x3>
			<y3>504.25</y3>
			<x4>305.927487</x4>
			<y4>495.5</y4>
			<x5>304.673199</x5>
			<y5>455.5</y5>
			<x6>301.537482</x6>
			<y6>415.5</y6>
			<x7>302.791769</x7>
			<y7>393</y7>
			<x8>302.791769</x8>
			<y8>375.5</y8>
			<x9>283.977462</x9>
			<y9>380.5</y9>
		</polygon>
	</object>
	<object>
		<name>RID</name>
		<pose>Unspecified</pose>
		<truncated>0</truncated>
		<difficult>0</difficult>
		<occluded>0</occluded>
		<bndbox>
			<xmin>304</xmin>
			<xmax>326</xmax>
			<ymin>378</ymin>
			<ymax>509</ymax>
		</bndbox>
		<polygon>
			<x1>309.063204</x1>
			<y1>503</y1>
			<x2>312.826066</x2>
			<y2>508</y2>
			<x3>325.368937</x3>
			<y3>493</y3>
			<x4>321.606075</x4>
			<y4>424.25</y4>
			<x5>319.097501</x5>
			<y5>376.75</y5>
			<x6>305.927487</x6>
			<y6>376.75</y6>
			<x7>303.418912</x7>
			<y7>393</y7>
			<x8>305.300343</x8>
			<y8>413</y8>
			<x9>306.55463</x9>
			<y9>446.75</y9>
			<x10>306.55463</x10>
			<y10>474.25</y10>
			<x11>309.063204</x11>
			<y11>503</y11>
		</polygon>
	</object>
	<object>
		<name>RPMD</name>
		<pose>Unspecified</pose>
		<truncated>0</truncated>
		<difficult>0</difficult>
		<occluded>0</occluded>
		<bndbox>
			<xmin>231</xmin>
			<xmax>262</xmax>
			<ymin>379</ymin>
			<ymax>519</ymax>
		</bndbox>
		<polygon>
			<x1>259.518863</x1>
			<y1>443</y1>
			<x2>261.400294</x2>
			<y2>411.75</y2>
			<x3>258.89172</x3>
			<y3>384.25</y3>
			<x4>240.704557</x4>
			<y4>378</y4>
			<x5>245.721705</x5>
			<y5>381.75</y5>
			<x6>235.060265</x6>
			<y6>424.25</y6>
			<x7>234.433121</x7>
			<y7>480.5</y7>
			<x8>230.043116</x8>
			<y8>504.25</y8>
			<x9>237.568839</x9>
			<y9>518</y9>
			<x10>251.365997</x10>
			<y10>490.5</y10>
			<x11>259.518863</x11>
			<y11>443</y11>
		</polygon>
	</object>
	<object>
		<name>RPMD</name>
		<pose>Unspecified</pose>
		<truncated>0</truncated>
		<difficult>0</difficult>
		<occluded>0</occluded>
		<bndbox>
			<xmin>200</xmin>
			<xmax>243</xmax>
			<ymin>369</ymin>
			<ymax>502</ymax>
		</bndbox>
		<polygon>
			<x1>223.144537</x1>
			<y1>465.5</y1>
			<x2>233.178834</x2>
			<y2>423</y2>
			<x3>240.077413</x3>
			<y3>399.25</y3>
			<x4>241.958844</x4>
			<y4>376.75</y4>
			<x5>223.771681</x5>
			<y5>368</y5>
			<x6>224.77511</x6>
			<y6>371.6</y6>
			<x7>218.754532</x7>
			<y7>398</y7>
			<x8>213.737384</x8>
			<y8>428</y8>
			<x9>204.33023</x9>
			<y9>469.25</y9>
			<x10>198.685938</x10>
			<y10>491.75</y10>
			<x11>207.465948</x11>
			<y11>500.5</y11>
			<x12>223.144537</x12>
			<y12>465.5</y12>
		</polygon>
	</object>
	<object>
		<name>RMD</name>
		<pose>Unspecified</pose>
		<truncated>0</truncated>
		<difficult>0</difficult>
		<occluded>0</occluded>
		<bndbox>
			<xmin>160</xmin>
			<xmax>222</xmax>
			<ymin>353</ymin>
			<ymax>495</ymax>
		</bndbox>
		<polygon>
			<x1>159.175894</x1>
			<y1>465.5</y1>
			<x2>191.160216</x2>
			<y2>494.25</y2>
			<x3>201.194512</x3>
			<y3>469.25</y3>
			<x4>209.347379</x4>
			<y4>426.75</y4>
			<x5>212.483097</x5>
			<y5>403</y5>
			<x6>220.635963</x6>
			<y6>374.25</y6>
			<x7>218.127389</x7>
			<y7>360.5</y7>
			<x8>201.194512</x8>
			<y8>359.25</y8>
			<x9>183.007349</x9>
			<y9>351.75</y9>
			<x10>181.125919</x10>
			<y10>380.5</y10>
			<x11>179.244488</x11>
			<y11>408</y11>
			<x12>165.44733</x12>
			<y12>455.5</y12>
			<x13>159.175894</x13>
			<y13>465.5</y13>
		</polygon>
	</object>
	<object>
		<name>RMD</name>
		<pose>Unspecified</pose>
		<truncated>0</truncated>
		<difficult>0</difficult>
		<occluded>0</occluded>
		<bndbox>
			<xmin>120</xmin>
			<xmax>183</xmax>
			<ymin>343</ymin>
			<ymax>454</ymax>
		</bndbox>
		<polygon>
			<x1>172.345909</x1>
			<y1>404.25</y1>
			<x2>179.244488</x2>
			<y2>383</y2>
			<x3>181.753062</x3>
			<y3>356.75</y3>
			<x4>145.378736</x4>
			<y4>341.75</y4>
			<x5>142.870162</x5>
			<y5>355.5</y5>
			<x6>140.361587</x6>
			<y6>390.5</y6>
			<x7>119.038707</x7>
			<y7>420.5</y7>
			<x8>126.564429</x8>
			<y8>453</y8>
			<x9>151.650171</x9>
			<y9>448</y9>
			<x10>172.345909</x10>
			<y10>404.25</y10>
		</polygon>
	</object>
	<object>
		<name>LID</name>
		<pose>Unspecified</pose>
		<truncated>0</truncated>
		<difficult>0</difficult>
		<occluded>0</occluded>
		<bndbox>
			<xmin>323</xmin>
			<xmax>346</xmax>
			<ymin>379</ymin>
			<ymax>497</ymax>
		</bndbox>
		<polygon>
			<x1>343.5561</x1>
			<y1>468</y1>
			<x2>339.166095</x2>
			<y2>430.5</y2>
			<x3>336.657521</x3>
			<y3>378</y3>
			<x4>321.606075</x4>
			<y4>378</y4>
			<x5>322.860363</x5>
			<y5>401.75</y5>
			<x6>323.487506</x6>
			<y6>426.75</y6>
			<x7>325.368937</x7>
			<y7>456.75</y7>
			<x8>329.758942</x8>
			<y8>495.5</y8>
			<x9>345.437531</x9>
			<y9>489.25</y9>
			<x10>343.5561</x10>
			<y10>468</y10>
		</polygon>
	</object>
	<object>
		<name>LID</name>
		<pose>Unspecified</pose>
		<truncated>0</truncated>
		<difficult>0</difficult>
		<occluded>0</occluded>
		<bndbox>
			<xmin>339</xmin>
			<xmax>366</xmax>
			<ymin>374</ymin>
			<ymax>498</ymax>
		</bndbox>
		<polygon>
			<x1>362.99755</x1>
			<y1>463</y1>
			<x2>358.607545</x2>
			<y2>416.75</y2>
			<x3>354.844684</x3>
			<y3>373</y3>
			<x4>337.911808</x4>
			<y4>376.75</y4>
			<x5>339.793239</x5>
			<y5>421.75</y5>
			<x6>339.793239</x6>
			<y6>448</y6>
			<x7>345.437531</x7>
			<y7>486.75</y7>
			<x8>349.827536</x8>
			<y8>496.75</y8>
			<x9>364.878981</x9>
			<y9>494.25</y9>
			<x10>362.99755</x10>
			<y10>463</y10>
		</polygon>
	</object>
	<object>
		<name>LCD</name>
		<pose>Unspecified</pose>
		<truncated>0</truncated>
		<difficult>0</difficult>
		<occluded>0</occluded>
		<bndbox>
			<xmin>358</xmin>
			<xmax>393</xmax>
			<ymin>377</ymin>
			<ymax>519</ymax>
		</bndbox>
		<polygon>
			<x1>384.320431</x1>
			<y1>445.5</y1>
			<x2>378.676139</x2>
			<y2>396.75</y2>
			<x3>374.913278</x3>
			<y3>375.5</y3>
			<x4>357.353258</x4>
			<y4>376.75</y4>
			<x5>358.607545</x5>
			<y5>426.75</y5>
			<x6>365.506124</x6>
			<y6>481.75</y6>
			<x7>379.303283</x7>
			<y7>518</y7>
			<x8>391.846154</x8>
			<y8>516.75</y8>
			<x9>389.964723</x9>
			<y9>504.25</y9>
			<x10>384.320431</x10>
			<y10>445.5</y10>
		</polygon>
	</object>
	<object>
		<name>LPMD</name>
		<pose>Unspecified</pose>
		<truncated>0</truncated>
		<difficult>0</difficult>
		<occluded>0</occluded>
		<bndbox>
			<xmin>381</xmin>
			<xmax>410</xmax>
			<ymin>380</ymin>
			<ymax>515</ymax>
		</bndbox>
		<polygon>
			<x1>379.930426</x1>
			<y1>379.25</y1>
			<x2>381.811857</x2>
			<y2>426.75</y2>
			<x3>391.21901</x3>
			<y3>494.25</y3>
			<x4>396.236159</x4>
			<y4>514.25</y4>
			<x5>408.77903</x5>
			<y5>508</y5>
			<x6>401.253307</x6>
			<y6>459.25</y6>
			<x7>398.117589</x7>
			<y7>413</y7>
			<x8>399.371877</x8>
			<y8>381.75</y8>
			<x9>379.930426</x9>
			<y9>379.25</y9>
		</polygon>
	</object>
	<object>
		<name>LPMD</name>
		<pose>Unspecified</pose>
		<truncated>0</truncated>
		<difficult>0</difficult>
		<occluded>0</occluded>
		<bndbox>
			<xmin>399</xmin>
			<xmax>437</xmax>
			<ymin>374</ymin>
			<ymax>508</ymax>
		</bndbox>
		<polygon>
			<x1>410.660461</x1>
			<y1>463</y1>
			<x2>428.22048</x2>
			<y2>506.75</y2>
			<x3>436.373346</x3>
			<y3>486.75</y3>
			<x4>425.711906</x4>
			<y4>421.75</y4>
			<x5>418.813327</x5>
			<y5>379.25</y5>
			<x6>398.117589</x6>
			<y6>373</y6>
			<x7>398.744733</x7>
			<y7>413</y7>
			<x8>410.660461</x8>
			<y8>463</y8>
		</polygon>
	</object>
	<object>
		<name>LMD</name>
		<pose>Unspecified</pose>
		<truncated>0</truncated>
		<difficult>0</difficult>
		<occluded>0</occluded>
		<bndbox>
			<xmin>417</xmin>
			<xmax>476</xmax>
			<ymin>358</ymin>
			<ymax>480</ymax>
		</bndbox>
		<polygon>
			<x1>447.66193</x1>
			<y1>479.25</y1>
			<x2>475.256247</x2>
			<y2>459.25</y2>
			<x3>456.44194</x3>
			<y3>395.5</y3>
			<x4>455.187653</x4>
			<y4>356.75</y4>
			<x5>434.491916</x5>
			<y5>361.75</y5>
			<x6>415.677609</x6>
			<y6>368</y6>
			<x7>429.474767</x7>
			<y7>418</y7>
			<x8>447.66193</x8>
			<y8>479.25</y8>
		</polygon>
	</object>
	<object>
		<name>LMD</name>
		<pose>Unspecified</pose>
		<truncated>0</truncated>
		<difficult>0</difficult>
		<occluded>0</occluded>
		<bndbox>
			<xmin>458</xmin>
			<xmax>515</xmax>
			<ymin>339</ymin>
			<ymax>473</ymax>
		</bndbox>
		<polygon>
			<x1>500.341989</x1>
			<y1>398</y1>
			<x2>491.561979</x2>
			<y2>360.5</y2>
			<x3>485.917687</x3>
			<y3>338</y3>
			<x4>457.696227</x4>
			<y4>350.5</y4>
			<x5>457.069084</x5>
			<y5>379.25</y5>
			<x6>464.594806</x6>
			<y6>396.75</y6>
			<x7>479.646252</x7>
			<y7>441.75</y7>
			<x8>501.596276</x8>
			<y8>471.75</y8>
			<x9>514.139147</x9>
			<y9>443</y9>
			<x10>500.341989</x10>
			<y10>398</y10>
		</polygon>
	</object>
	<object>
		<name>LMD</name>
		<pose>Unspecified</pose>
		<truncated>0</truncated>
		<difficult>0</difficult>
		<occluded>0</occluded>
		<bndbox>
			<xmin>491</xmin>
			<xmax>538</xmax>
			<ymin>322</ymin>
			<ymax>443</ymax>
		</bndbox>
		<polygon>
			<x1>516.020578</x1>
			<y1>441.75</y1>
			<x2>537.343459</x2>
			<y2>411.75</y2>
			<x3>521.66487</x3>
			<y3>320.5</y3>
			<x4>490.307692</x4>
			<y4>333</y4>
			<x5>489.680549</x5>
			<y5>348</y5>
			<x6>499.714846</x6>
			<y6>391.75</y6>
			<x7>516.020578</x7>
			<y7>441.75</y7>
		</polygon>
	</object>
</annotation>
